__init__.py
plugins/__init__.py
plugins/cli_azure_keyvault.py
plugins/cli_k8s.py
tenvplate/__init__.py
tenvplate/cli.py
tenvplate/processing.py
tenvplate/progress.py
tenvplate/protocols.py
tenvplate/resources.py
tenvplate-0.0.4.dist-info/LICENSE
tenvplate-0.0.4.dist-info/METADATA
tenvplate-0.0.4.dist-info/WHEEL
tenvplate-0.0.4.dist-info/entry_points.txt
tenvplate-0.0.4.dist-info/top_level.txt
tenvplate-0.0.4.dist-info/RECORD
