Metadata-Version: 2.1
Name: tenvplate
Version: 0.0.4
Summary: Generate .env files from templates and secrets managers
Author-email: Gabriele Calvo <gcalvo87@gmail.com>
Keywords: env,dotenv,template,secret
Classifier: Development Status :: 4 - Beta
Classifier: Intended Audience :: Developers
Classifier: License :: OSI Approved :: MIT License
Classifier: Programming Language :: Python :: 3
Classifier: Operating System :: OS Independent
Requires-Python: >=3.10
License-File: LICENSE
